scd/__init__.py
scd/config.py
scd/files.py
scd/main.py
scd/utils.py
scd/version.py
scd-1.2.3.dist-info/DESCRIPTION.rst
scd-1.2.3.dist-info/METADATA
scd-1.2.3.dist-info/RECORD
scd-1.2.3.dist-info/WHEEL
scd-1.2.3.dist-info/entry_points.txt
scd-1.2.3.dist-info/metadata.json
scd-1.2.3.dist-info/top_level.txt
scd-1.2.3.dist-info/zip-safe
