Metadata-Version: 2.0
Name: scd
Version: 1.2.3
Summary: Something Completely different
Home-page: https://github.com/9seconds/scd
Author: Sergey Arkhipov
Author-email: nineseconds@yandex.ru
License: MIT
Platform: UNKNOWN
Classifier: Development Status :: 5 - Production/Stable
Classifier: Environment :: Console
Classifier: Intended Audience :: Developers
Classifier: Intended Audience :: System Administrators
Classifier: License :: OSI Approved :: MIT License
Classifier: Operating System :: OS Independent
Classifier: Programming Language :: Python
Classifier: Programming Language :: Python :: 2
Classifier: Programming Language :: Python :: 2.7
Classifier: Programming Language :: Python :: 3
Classifier: Programming Language :: Python :: 3.3
Classifier: Programming Language :: Python :: 3.4
Classifier: Programming Language :: Python :: 3.5
Classifier: Programming Language :: Python :: 3.6
Classifier: Programming Language :: Python :: Implementation :: PyPy
Classifier: Topic :: Software Development
Classifier: Topic :: Software Development :: Version Control
Classifier: Topic :: Utilities
Requires-Python: >=2.7
Requires-Dist: jinja2 (<3,>=2.6)
Requires-Dist: jsonschema (>=2.5,<3)
Requires-Dist: packaging (>=16,<17)
Requires-Dist: semver (>=2,<3)
Requires-Dist: six (>=1.10)
Provides-Extra: colors
Requires-Dist: colorama (<0.4,>=0.3); extra == 'colors'
Provides-Extra: simplejson
Requires-Dist: simplejson; extra == 'simplejson'
Provides-Extra: toml
Requires-Dist: toml (~=0.9.2); extra == 'toml'
Provides-Extra: yaml
Requires-Dist: PyYAML (~=3.10); extra == 'yaml'
